remopy/__init__.py
remopy/_data.py
remopy/_quantify.py
remopy/py.typed
remopy/data/REMOv1_GRCh38.bed.gz
remopy/data/REMOv1_GRCh38.bed.gz.tbi
remopy/data/__init__.py
remopy/data/cl_ids.json
remopy/data/metadata.parquet
remopy/data/terms.json
remopy/data/tissues.json
remopy-1.0.1.dist-info/METADATA
remopy-1.0.1.dist-info/WHEEL
remopy-1.0.1.dist-info/licenses/LICENSE
remopy-1.0.1.dist-info/RECORD
