Metadata-Version: 2.4
Name: remopy
Version: 1.0.1
Summary: REMO v1 regulatory element modules for GRCh38
Project-URL: Homepage, https://github.com/shahrozeabbas/remopy
Project-URL: Repository, https://github.com/shahrozeabbas/remopy
Author: Shahroze Abbas
License: The Artistic License 2.0
License-File: LICENSE
Keywords: chromatin,genomics,regulatory-elements,scATAC,single-cell
Classifier: Development Status :: 4 - Beta
Classifier: Intended Audience :: Science/Research
Classifier: License :: OSI Approved :: Artistic License
Classifier: Programming Language :: Python :: 3
Classifier: Programming Language :: Python :: 3.10
Classifier: Programming Language :: Python :: 3.11
Classifier: Programming Language :: Python :: 3.12
Classifier: Topic :: Scientific/Engineering :: Bio-Informatics
Requires-Python: >=3.10
Requires-Dist: polars>=1.0
Provides-Extra: all
Requires-Dist: anndata>=0.10; extra == 'all'
Requires-Dist: numpy>=1.24; extra == 'all'
Requires-Dist: polars-bio>=0.2; extra == 'all'
Requires-Dist: scipy>=1.10; extra == 'all'
Provides-Extra: quantify
Requires-Dist: anndata>=0.10; extra == 'quantify'
Requires-Dist: numpy>=1.24; extra == 'quantify'
Requires-Dist: polars-bio>=0.2; extra == 'quantify'
Requires-Dist: scipy>=1.10; extra == 'quantify'
